nonebot_plugin_essence_message/Helper.py
nonebot_plugin_essence_message/__init__.py
nonebot_plugin_essence_message/config.py
nonebot_plugin_essence_message/dataset.py
nonebot_plugin_essence_message-0.6.0.dist-info/LICENSE
nonebot_plugin_essence_message-0.6.0.dist-info/METADATA
nonebot_plugin_essence_message-0.6.0.dist-info/WHEEL
nonebot_plugin_essence_message-0.6.0.dist-info/RECORD
